launchlibrary/__init__.py
launchlibrary/api.py
launchlibrary/async_models.py
launchlibrary/exceptions.py
launchlibrary/models.py
launchlibrary/utils.py
python_launch_library-0.6.dist-info/LICENSE
python_launch_library-0.6.dist-info/METADATA
python_launch_library-0.6.dist-info/WHEEL
python_launch_library-0.6.dist-info/top_level.txt
python_launch_library-0.6.dist-info/RECORD
