Metadata-Version: 2.1
Name: python-launch-library
Version: 0.6
Summary: A wrapper for the launchlibrary.net API
Home-page: https://github.com/Plutoberth/python-launch-library
Author: Nir Harel
Author-email: nir@nirharel.space
License: UNKNOWN
Platform: UNKNOWN
Classifier: Programming Language :: Python :: 3
Classifier: License :: OSI Approved :: Apache Software License
Classifier: Operating System :: OS Independent
Classifier: Development Status :: 4 - Beta
Classifier: Programming Language :: Python :: 3.6
Requires-Python: >=3.6
Requires-Dist: requests
Requires-Dist: python-dateutil
Requires-Dist: aiohttp
Requires-Dist: unidecode
